fsm_llm/__init__.py
fsm_llm/fsm.py
fsm_llm/llm_handler.py
fsm_llm/state_models.py
fsm_llm/utils.py
fsm_llm-0.1.3.dist-info/LICENSE
fsm_llm-0.1.3.dist-info/METADATA
fsm_llm-0.1.3.dist-info/WHEEL
fsm_llm-0.1.3.dist-info/top_level.txt
fsm_llm-0.1.3.dist-info/RECORD
